agentop/__init__.py
agentop/__main__.py
agentop/core/__init__.py
agentop/core/constants.py
agentop/core/models.py
agentop/monitors/__init__.py
agentop/monitors/antigravity.py
agentop/monitors/claude_code.py
agentop/monitors/codex.py
agentop/monitors/opencode.py
agentop/monitors/process.py
agentop/parsers/__init__.py
agentop/parsers/antigravity_quota_api.py
agentop/parsers/claude_logs.py
agentop/parsers/claude_rate_limits.py
agentop/parsers/codex_rate_limits.py
agentop/parsers/codex_stats.py
agentop/parsers/google_auth.py
agentop/parsers/opencode_cache.py
agentop/parsers/opencode_stats.py
agentop/parsers/stats_parser.py
agentop/ui/__init__.py
agentop/ui/app.py
agentop/ui/widgets/__init__.py
agentop/ui/widgets/agent_panel.py
agentop/ui/widgets/antigravity_panel.py
agentop/ui/widgets/opencode_panel.py
agentop-0.2.0.dist-info/licenses/LICENSE
agentop-0.2.0.dist-info/METADATA
agentop-0.2.0.dist-info/WHEEL
agentop-0.2.0.dist-info/entry_points.txt
agentop-0.2.0.dist-info/top_level.txt
agentop-0.2.0.dist-info/RECORD
