Metadata-Version: 2.4
Name: agentop
Version: 0.2.0
Summary: A terminal UI tool for monitoring local AI coding agents (Claude Code, etc.)
Author: Yuanhong Yu
License-Expression: MIT
Project-URL: Homepage, https://github.com/dadwadw233/agentop
Project-URL: Repository, https://github.com/dadwadw233/agentop
Project-URL: Issues, https://github.com/dadwadw233/agentop/issues
Keywords: ai,monitoring,tui,claude,agent
Classifier: Development Status :: 3 - Alpha
Classifier: Environment :: Console
Classifier: Intended Audience :: Developers
Classifier: Programming Language :: Python :: 3
Classifier: Programming Language :: Python :: 3.9
Classifier: Programming Language :: Python :: 3.10
Classifier: Programming Language :: Python :: 3.11
Classifier: Programming Language :: Python :: 3.12
Classifier: Topic :: System :: Monitoring
Requires-Python: >=3.9
License-File: LICENSE
Requires-Dist: textual>=0.88.0
Requires-Dist: rich>=13.9.0
Requires-Dist: psutil>=6.1.0
Requires-Dist: pydantic>=2.10.0
Requires-Dist: aiofiles>=24.1.0
Requires-Dist: httpx>=0.28.0
Requires-Dist: pyyaml>=6.0.2
Requires-Dist: platformdirs>=4.3.0
Provides-Extra: dev
Requires-Dist: pytest>=8.0.0; extra == "dev"
Requires-Dist: pytest-asyncio>=0.23.0; extra == "dev"
Requires-Dist: black>=24.0.0; extra == "dev"
Requires-Dist: ruff>=0.6.0; extra == "dev"
Dynamic: license-file
